fbrefstats/__init__.py
fbrefstats/fbrefstats.py
fbrefstats-0.1.13.dist-info/METADATA
fbrefstats-0.1.13.dist-info/WHEEL
fbrefstats-0.1.13.dist-info/licenses/LICENSE.txt
fbrefstats-0.1.13.dist-info/RECORD
