Metadata-Version: 2.4
Name: fbrefstats
Version: 0.1.13
Summary: A Python script to scrape football data from FBRef
Project-URL: Homepage, https://github.com/mbrahimi25/fbrefstats
Project-URL: Documentation, https://github.com/mbrahimi25/fbrefstats/blob/main/DOCUMENTATION.md
Author: Mohamed Brahimi
License:                     GNU GENERAL PUBLIC LICENSE
License-File: LICENSE.txt
Keywords: FBRef,football,scraping,soccer,webscraping
Classifier: License :: OSI Approved :: GNU General Public License v2 (GPLv2)
Classifier: Operating System :: OS Independent
Classifier: Programming Language :: Python :: 3
Requires-Python: >=3.6
Requires-Dist: bs4
Requires-Dist: fake-http-header
Requires-Dist: html5lib
Requires-Dist: lxml
Requires-Dist: pandas
Requires-Dist: requests
